<?xml version="1.0"?>
<!--<!DOCTYPE metadata SYSTEM "http://www.esri.com/metadata/esriprof80.dtd">-->
<metadata xml:lang="en"><Esri><CreaDate>20180605</CreaDate><CreaTime>10441100</CreaTime><SyncOnce>TRUE</SyncOnce><DataProperties><lineage><Process ToolSource="c:\program files (x86)\arcgis\desktop10.1\ArcToolbox\Toolboxes\Data Management Tools.tbx\DefineProjection" Date="20140608" Time="095251">DefineProjection "mainstream awash_geosusceptibility" GEOGCS['GCS_WGS_1984',DATUM['D_WGS_1984',SPHEROID['WGS_1984',6378137.0,298.257223563]],PRIMEM['Greenwich',0.0],UNIT['Degree',0.0174532925199433]]</Process><Process ToolSource="c:\program files (x86)\arcgis\desktop10.1\ArcToolbox\Toolboxes\Data Management Tools.tbx\DefineProjection" Date="20140608" Time="095535">DefineProjection "mainstream awash_geosusceptibility" PROJCS['WGS_1984_UTM_Zone_37N',GEOGCS['GCS_WGS_1984',DATUM['D_WGS_1984',SPHEROID['WGS_1984',6378137.0,298.257223563]],PRIMEM['Greenwich',0.0],UNIT['Degree',0.0174532925199433]],PROJECTION['Transverse_Mercator'],PARAMETER['False_Easting',500000.0],PARAMETER['False_Northing',0.0],PARAMETER['Central_Meridian',39.0],PARAMETER['Scale_Factor',0.9996],PARAMETER['Latitude_Of_Origin',0.0],UNIT['Meter',1.0]]</Process><Process ToolSource="c:\program files (x86)\arcgis\desktop10.1\ArcToolbox\Toolboxes\Data Management Tools.tbx\DefineProjection" Date="20140608" Time="095701">DefineProjection "mainstream awash_geosusceptibility" PROJCS['WGS_1984_UTM_Zone_37N',GEOGCS['GCS_WGS_1984',DATUM['D_WGS_1984',SPHEROID['WGS_1984',6378137.0,298.257223563]],PRIMEM['Greenwich',0.0],UNIT['Degree',0.0174532925199433]],PROJECTION['Transverse_Mercator'],PARAMETER['False_Easting',500000.0],PARAMETER['False_Northing',0.0],PARAMETER['Central_Meridian',39.0],PARAMETER['Scale_Factor',0.9996],PARAMETER['Latitude_Of_Origin',0.0],UNIT['Meter',1.0]]</Process></lineage></DataProperties><ArcGISFormat>1.0</ArcGISFormat></Esri><idinfo><citation><citeinfo><onlink Sync="TRUE">\\DESK3\E$\awash river basin\geomorphology\awash mainstream geomorphology\geo-reaches</onlink></citeinfo></citation></idinfo><distInfo><distributor><distorTran><onLineSrc><linkage Sync="TRUE">file://\\DESK3\E$\awash river basin\geomorphology\awash mainstream geomorphology\geo-reaches</linkage><protocol Sync="TRUE">Local Area Network</protocol></onLineSrc></distorTran></distributor></distInfo><dataqual><lineage><procstep><procdesc Sync="TRUE">Dataset copied.</procdesc><srcused Sync="TRUE">E:\AWASH RIVER BASIN\FINAL FIGURES\geo-reaches</srcused><date Sync="TRUE">20241226</date><time Sync="TRUE">16053300</time></procstep></lineage></dataqual></metadata>
